asymcaus/__init__.py
asymcaus/hatemi_j_asymmetric_causality_FINAL.py
asymcaus/visualization.py
asymcauss-1.0.1.dist-info/licenses/LICENSE
asymcauss-1.0.1.dist-info/METADATA
asymcauss-1.0.1.dist-info/WHEEL
asymcauss-1.0.1.dist-info/top_level.txt
asymcauss-1.0.1.dist-info/RECORD
