Metadata-Version: 2.4
Name: asymcauss
Version: 1.0.1
Summary: Asymmetric Causality Tests compatible with GAUSS implementation
Home-page: https://github.com/merwanroudane/asymcauss
Author: Dr. Merwan Roudane
Author-email: "Dr. Merwan Roudane" <merwanroudane920@gmail.com>
License: MIT
Requires-Python: >=3.7
License-File: LICENSE
Requires-Dist: numpy>=1.21.0
Requires-Dist: pandas>=1.3.0
Requires-Dist: scipy>=1.6.0
Requires-Dist: statsmodels>=0.13.0
Requires-Dist: matplotlib>=3.4.0
Dynamic: author
Dynamic: home-page
Dynamic: license-file
Dynamic: requires-python
